rtl/dg_requant.v
`timescale 1ns/1ps
// Custom symmetric INT8 contract; NOT TFLite bit-exact requantization.
// multiplier must be 0..2^31-1, shift 0..62. Round ties away from zero.
module dg_requant(
 input signed [31:0] acc, input signed [31:0] multiplier,
 input [5:0] shift, input relu, output reg signed [7:0] value
);
 reg signed [63:0] product, rounded;
 reg [63:0] magnitude, half, scaled;
 always @* begin
   product = acc * multiplier;
   magnitude = product[63] ? -product : product;
   half = (shift == 0) ? 64'd0 : (64'd1 << (shift-1));
   scaled = (magnitude + half) >> shift;
   rounded = product[63] ? -$signed(scaled) : $signed(scaled);
   if (relu && rounded < 0) value = 0;
   else if (rounded > 127) value = 8'sd127;
   else if (rounded < -128) value = -8'sd128;
   else value = rounded[7:0];
 end
endmodule

rtl/dg_mac_lane.v
`timescale 1ns/1ps
module dg_mac_lane(
 input clk, input rst_n, input clear, input enable,
 input signed [7:0] a, input signed [7:0] w,
 input signed [31:0] bias, output reg signed [31:0] acc
);
 wire signed [15:0] product = a * w;
 wire signed [31:0] extended_product = {{16{product[15]}},product};
 always @(posedge clk) begin
   if (!rst_n) acc <= 0;
   else if (clear) acc <= bias;
   else if (enable) acc <= acc + extended_product;
 end
endmodule

rtl/dg_tile_ram.v
`timescale 1ns/1ps
// One synchronous-read bank. Contents are intentionally not reset.
module dg_tile_ram #(parameter DEPTH=256)(
 input clk, input we, input [15:0] waddr, input signed [7:0] wdata,
 input re, input [15:0] raddr, output reg signed [7:0] q
);
 (* ramstyle = "M10K" *) reg signed [7:0] mem [0:DEPTH-1];
 always @(posedge clk) begin
   if (we && waddr < DEPTH) mem[waddr] <= wdata;
   if (re && raddr < DEPTH) q <= mem[raddr];
 end
endmodule

rtl/dg_tile_core.v
`timescale 1ns/1ps
// Output-stationary tile: one activation vector, LANES output channels.
// Host packs convolution windows and schedules tiles. No DMA in this module.
module dg_tile_core #(parameter LANES=8, DEPTH=256)(
 input clk, input rst_n,
 input start, input [15:0] length, input model_id, input relu,
 input act_we, input [15:0] act_addr, input signed [7:0] act_data,
 input weight_we, input [15:0] weight_lane, input [15:0] weight_addr,
 input signed [7:0] weight_data,
 input param_we, input [15:0] param_lane, input [1:0] param_kind,
 input [31:0] param_data,
 output busy, output load_ready, output reg done, output reg error,
 output out_valid, input out_ready, output [15:0] out_lane,
 output out_model, output signed [31:0] out_acc,
 output signed [7:0] out_q
);
 localparam IDLE=0, FETCH=1, MAC=2, FINISH=3, EMIT=4;
 reg [2:0] state;
 reg [15:0] k, count, lane;
 reg active_model, active_relu;
 reg signed [31:0] biases [0:LANES-1];
 reg signed [31:0] multipliers [0:LANES-1];
 reg [5:0] shifts [0:LANES-1];
 wire signed [7:0] a;
 wire signed [31:0] accumulators [0:LANES-1];
 wire accept_start = start && state==IDLE && length>0 && length<=DEPTH;
 assign busy = state != IDLE;
 assign load_ready = !busy;
 assign out_valid = state == EMIT;
 assign out_lane = lane;
 assign out_model = active_model;
 assign out_acc = accumulators[lane];
 dg_tile_ram #(DEPTH) input_bank(clk, act_we && !busy,
   act_addr, act_data, state==FETCH, k, a);
 genvar g;
 generate for(g=0; g<LANES; g=g+1) begin: banks
   wire signed [7:0] w;
   dg_tile_ram #(DEPTH) weight_bank(clk,
     weight_we && !busy && weight_lane==g,
     weight_addr, weight_data, state==FETCH, k, w);
   dg_mac_lane mac(clk,rst_n,accept_start,state==MAC,a,w,
     biases[g],accumulators[g]);
 end endgenerate
 // One shared requantizer selected by output lane.
 dg_requant quant(out_acc,multipliers[lane],shifts[lane],active_relu,out_q);
 integer i;
 always @(posedge clk) begin
   if(!rst_n) begin
     state<=IDLE; k<=0; count<=0; lane<=0;
     active_model<=0; active_relu<=0; done<=0; error<=0;
     for(i=0;i<LANES;i=i+1) begin
       biases[i]<=0; multipliers[i]<=1; shifts[i]<=0;
     end
   end else begin
     done<=0; error<=0;
     if(param_we && !busy && param_lane<LANES) begin
       case(param_kind)
         0: biases[param_lane]<=param_data;
         1: if(!param_data[31]) multipliers[param_lane]<=param_data;
            else error<=1;
         2: if(param_data<=62) shifts[param_lane]<=param_data[5:0];
            else error<=1;
         default: error<=1;
       endcase
     end
     if(start && busy) error<=1;
     case(state)
       IDLE: if(start) begin
         if(length==0 || length>DEPTH) error<=1;
         else begin
           count<=length; k<=0; lane<=0;
           active_model<=model_id; active_relu<=relu; state<=FETCH;
         end
       end
       FETCH: state<=MAC;
       MAC: if(k==count-1) state<=FINISH;
            else begin k<=k+1; state<=FETCH; end
       FINISH: state<=EMIT;
       EMIT: if(out_ready) begin
         if(lane==LANES-1) begin state<=IDLE; done<=1; end
         else lane<=lane+1;
       end
       default: state<=IDLE;
     endcase
   end
 end
endmodule

rtl/dg_csr_top.v
`timescale 1ns/1ps
// Avalon-MM 32-bit agent: byte addresses, readLatency=0, no bursts.
// Full-word aligned writes only. Single clock domain, synchronous reset.
module dg_csr_top #(parameter LANES=8, DEPTH=256)(
 input clk, input rst_n, input [7:0] address,
 input read, input write, input [3:0] byteenable,
 input [31:0] writedata, output reg [31:0] readdata,
 output waitrequest, output irq
);
 localparam [15:0] LANES_VALUE=LANES, DEPTH_VALUE=DEPTH;
 reg [15:0] length, index_reg, lane_reg;
 reg model_id, relu, sticky_done, sticky_error;
 reg [31:0] cycles;
 wire busy, done, error, valid, model;
 wire [15:0] out_lane;
 wire signed [31:0] out_acc;
 wire signed [7:0] out_q;
 wire aligned = address[1:0]==0;
 wire wr = write && aligned && byteenable==4'hf;
 wire ctrl = wr && address==8'h00;
 wire load = wr && !busy;
 wire pop = ctrl && writedata[2];
 assign waitrequest=0;
 assign irq=sticky_done || sticky_error;
 dg_tile_core #(LANES,DEPTH) core(
   .clk(clk),.rst_n(rst_n),.start(ctrl && writedata[0]),
   .length(length),.model_id(model_id),.relu(relu),
   .act_we(load && address==8'h18),.act_addr(index_reg),
   .act_data(writedata[7:0]),
   .weight_we(load && address==8'h1c),.weight_lane(lane_reg),
   .weight_addr(index_reg),.weight_data(writedata[7:0]),
   .param_we(load && (address==8'h20 || address==8'h24 || address==8'h28)),
   .param_lane(lane_reg),
   .param_kind(address==8'h20 ? 2'd0 : address==8'h24 ? 2'd1 : 2'd2),
   .param_data(writedata),.busy(busy),.load_ready(),
   .done(done),.error(error),.out_valid(valid),.out_ready(pop),
   .out_lane(out_lane),.out_model(model),.out_acc(out_acc),.out_q(out_q));
 always @* begin
   readdata=0;
   if(read && aligned) case(address)
     8'h04: readdata={28'd0,sticky_error,sticky_done,valid,busy};
     8'h08: readdata={16'd0,length};
     8'h0c: readdata={30'd0,relu,model_id};
     8'h10: readdata={16'd0,index_reg};
     8'h14: readdata={16'd0,lane_reg};
     8'h30: readdata={{24{out_q[7]}},out_q};
     8'h34: readdata=out_acc;
     8'h38: readdata={15'd0,model,out_lane};
     8'h3c: readdata=cycles;
     8'h40: readdata={16'd0,LANES_VALUE};
     8'h44: readdata={16'd0,DEPTH_VALUE};
     default: readdata=0;
   endcase
 end
 always @(posedge clk) begin
   if(!rst_n) begin
     length<=1; index_reg<=0; lane_reg<=0; model_id<=0; relu<=0;
     sticky_done<=0; sticky_error<=0; cycles<=0;
   end else begin
     if(ctrl && writedata[1]) begin sticky_done<=0; sticky_error<=0; end
     if(ctrl && writedata[0] && !busy) begin cycles<=0; sticky_done<=0; end
     else if(busy) cycles<=cycles+1;
     if(done) sticky_done<=1;
     if(error) sticky_error<=1;
     if(write && (!aligned || byteenable!=4'hf)) sticky_error<=1;
     if(wr && !ctrl && busy) sticky_error<=1;
     if(load) case(address)
       8'h08: if(writedata<=DEPTH && writedata>0) length<=writedata[15:0];
              else sticky_error<=1;
       8'h0c: if(writedata<=3) begin model_id<=writedata[0]; relu<=writedata[1]; end
              else sticky_error<=1;
       8'h10: if(writedata<DEPTH) index_reg<=writedata[15:0]; else sticky_error<=1;
       8'h14: if(writedata<LANES) lane_reg<=writedata[15:0]; else sticky_error<=1;
       8'h00,8'h18,8'h1c,8'h20,8'h24,8'h28: ;
       default: sticky_error<=1;
     endcase
   end
 end
endmodule

tb/tb_csr.v
`timescale 1ns/1ps
module tb_csr;
 reg clk=0; always #5 clk=~clk;
 reg rst_n=0;
 reg [7:0] address=0;
 reg read=0, write=0;
 reg [3:0] byteenable=15;
 reg [31:0] writedata=0;
 wire [31:0] readdata;
 wire waitrequest,irq;
 dg_csr_top #(4,256) dut(clk,rst_n,address,read,write,byteenable,
   writedata,readdata,waitrequest,irq);
 integer a[0:255]; integer w[0:3][0:255];
 integer b[0:3]; integer m[0:3]; integer sh[0:3];
 integer trial,k,j,n,expected,scaled,sign,seed=93217;
 reg [31:0] got;
 task wr;
   input [7:0] addr; input [31:0] val;
   begin
     @(negedge clk); address=addr; writedata=val; write=1;
     @(negedge clk); write=0;
   end
 endtask
 task rd;
   input [7:0] addr; output [31:0] val;
   begin
     @(negedge clk); address=addr; read=1;
     #1; val=readdata;
     @(negedge clk); read=0;
   end
 endtask
 task wait_valid;
   integer timeout;
   reg [31:0] s;
   begin
     timeout=0; s=0;
     while(!s[1] && timeout<2000) begin rd(4,s); timeout=timeout+1; end
     if(!s[1]) $fatal(1,"timeout");
   end
 endtask
 initial begin
   $dumpfile("tile.vcd"); $dumpvars(0,tb_csr);
   repeat(3) @(negedge clk); rst_n=1;
   for(trial=0;trial<12;trial=trial+1) begin
     n=trial==0 ? 1 : trial==1 ? 256 : 3+trial*2;
     wr(0,2); wr(8,n); wr(12,trial%4);
     for(k=0;k<n;k=k+1) begin
       a[k]=($random(seed)&255)-128;
       if(trial==0) a[k]=-128;
       wr(16,k); wr(24,a[k]);
     end
     for(j=0;j<4;j=j+1) begin
       b[j]=j*5-10; m[j]=j+1; sh[j]=trial%6;
       wr(20,j); wr(32,b[j]); wr(36,m[j]); wr(40,sh[j]);
       for(k=0;k<n;k=k+1) begin
         w[j][k]=($random(seed)&255)-128;
         if(trial==0) w[j][k]=j==0 ? -128 : 127;
         wr(16,k); wr(28,w[j][k]);
       end
     end
     wr(0,1); wait_valid;
     // Attempted config mutation while busy must be rejected.
     wr(12,3); rd(4,got);
     if(!got[3]) $fatal(1,"busy write must set error");
     for(j=0;j<4;j=j+1) begin
       expected=b[j];
       for(k=0;k<n;k=k+1) expected=expected+a[k]*w[j][k];
       rd(52,got);
       if($signed(got)!=expected) $fatal(1,"acc t=%0d lane=%0d got=%0d expected=%0d",trial,j,$signed(got),expected);
       scaled=expected*m[j]; sign=scaled<0 ? -1 : 1;
       if(scaled<0) scaled=-scaled;
       if(sh[j]>0) scaled=(scaled+(1<<(sh[j]-1)))>>sh[j];
       scaled=scaled*sign;
       if((trial%4)>=2 && scaled<0) scaled=0;
       if(scaled>127) scaled=127;
       if(scaled< -128) scaled=-128;
       rd(48,got);
       if($signed(got)!=scaled) $fatal(1,"quant mismatch");
       // Output must remain stable without POP, including model/lane tag.
       repeat(3) @(negedge clk);
       rd(52,got); if($signed(got)!=expected) $fatal(1,"backpressure");
       rd(56,got);
       if(got!={15'd0,(trial%2==1),16'(j)}) $fatal(1,"tag mismatch");
       wr(0,4);
     end
     repeat(3) @(negedge clk);
     rd(4,got); if(!got[2] || got[0]) $fatal(1,"completion status");
   end
   wr(0,2); wr(8,0); rd(4,got);
   if(!got[3]) $fatal(1,"invalid length");
   wr(0,2); wr(8,257); rd(4,got);
   if(!got[3]) $fatal(1,"oversized length");
   wr(0,2); wr(20,0); wr(40,63);
   repeat(3) @(negedge clk); rd(4,got);
   if(!got[3]) $fatal(1,"invalid shift");
   wr(0,2); wr(36,32'h80000000);
   repeat(3) @(negedge clk); rd(4,got);
   if(!got[3]) $fatal(1,"invalid multiplier");
   wr(0,2); byteenable=1; wr(8,1); byteenable=15; rd(4,got);
   if(!got[3]) $fatal(1,"partial write rejection");
   $display("PASS: 12 tiles, 48 dot products; reload, signed extremes, ReLU, saturation, backpressure, busy lock, CSR errors");
   $finish;
 end
 initial begin #10000000; $fatal(1,"watchdog"); end
endmodule

tile.vcd
$date
	Wed Oct 07 23:42:19 2026
$end
$version
	Icarus Verilog
$end
$timescale
	1ps
$end
$scope module tb_csr $end
$var wire 1 ! waitrequest $end
$var wire 32 " readdata [31:0] $end
$var wire 1 # irq $end
$var reg 8 $ address [7:0] $end
$var reg 4 % byteenable [3:0] $end
$var reg 1 & clk $end
$var reg 32 ' got [31:0] $end
$var reg 1 ( read $end
$var reg 1 ) rst_n $end
$var reg 1 * write $end
$var reg 32 + writedata [31:0] $end
$var integer 32 , expected [31:0] $end
$var integer 32 - j [31:0] $end
$var integer 32 . k [31:0] $end
$var integer 32 / n [31:0] $end
$var integer 32 0 scaled [31:0] $end
$var integer 32 1 seed [31:0] $end
$var integer 32 2 sign [31:0] $end
$var integer 32 3 trial [31:0] $end
$scope module dut $end
$var wire 8 4 address [7:0] $end
$var wire 4 5 byteenable [3:0] $end
$var wire 1 & clk $end
$var wire 1 6 ctrl $end
$var wire 1 # irq $end
$var wire 1 7 load $end
$var wire 1 8 pop $end
$var wire 1 ( read $end
$var wire 1 ) rst_n $end
$var wire 1 ! waitrequest $end
$var wire 1 9 wr $end
$var wire 1 * write $end
$var wire 32 : writedata [31:0] $end
$var wire 1 ; valid $end
$var wire 8 < out_q [7:0] $end
$var wire 16 = out_lane [15:0] $end
$var wire 32 > out_acc [31:0] $end
$var wire 1 ? model $end
$var wire 1 @ error $end
$var wire 1 A done $end
$var wire 1 B busy $end
$var wire 1 C aligned $end
$var parameter 32 D DEPTH $end
$var parameter 16 E DEPTH_VALUE $end
$var parameter 32 F LANES $end
$var parameter 16 G LANES_VALUE $end
$var reg 32 H cycles [31:0] $end
$var reg 16 I index_reg [15:0] $end
$var reg 16 J lane_reg [15:0] $end
$var reg 16 K length [15:0] $end
$var reg 1 L model_id $end
$var reg 32 M readdata [31:0] $end
$var reg 1 N relu $end
$var reg 1 O sticky_done $end
$var reg 1 P sticky_error $end
$scope module core $end
$var wire 1 Q accept_start $end
$var wire 16 R act_addr [15:0] $end
$var wire 8 S act_data [7:0] $end
$var wire 1 T act_we $end
$var wire 1 & clk $end
$var wire 16 U length [15:0] $end
$var wire 1 L model_id $end
$var wire 32 V out_acc [31:0] $end
$var wire 16 W out_lane [15:0] $end
$var wire 1 ? out_model $end
$var wire 1 8 out_ready $end
$var wire 32 X param_data [31:0] $end
$var wire 2 Y param_kind [1:0] $end
$var wire 16 Z param_lane [15:0] $end
$var wire 1 [ param_we $end
$var wire 1 N relu $end
$var wire 1 ) rst_n $end
$var wire 1 \ start $end
$var wire 16 ] weight_addr [15:0] $end
$var wire 8 ^ weight_data [7:0] $end
$var wire 16 _ weight_lane [15:0] $end
$var wire 1 ` weight_we $end
$var wire 1 ; out_valid $end
$var wire 8 a out_q [7:0] $end
$var wire 1 b load_ready $end
$var wire 1 B busy $end
$var wire 8 c a [7:0] $end
$var parameter 32 d DEPTH $end
$var parameter 32 e EMIT $end
$var parameter 32 f FETCH $end
$var parameter 32 g FINISH $end
$var parameter 32 h IDLE $end
$var parameter 32 i LANES $end
$var parameter 32 j MAC $end
$var reg 1 k active_model $end
$var reg 1 l active_relu $end
$var reg 16 m count [15:0] $end
$var reg 1 A done $end
$var reg 1 @ error $end
$var reg 16 n k [15:0] $end
$var reg 16 o lane [15:0] $end
$var reg 3 p state [2:0] $end
$var integer 32 q i [31:0] $end
$scope begin banks[0] $end
$var wire 8 r w [7:0] $end
$var parameter 2 s g $end
$scope module mac $end
$var wire 32 t bias [31:0] $end
$var wire 1 Q clear $end
$var wire 1 & clk $end
$var wire 1 u enable $end
$var wire 1 ) rst_n $end
$var wire 8 v w [7:0] $end
$var wire 16 w product [15:0] $end
$var wire 32 x extended_product [31:0] $end
$var wire 8 y a [7:0] $end
$var reg 32 z acc [31:0] $end
$upscope $end
$scope module weight_bank $end
$var wire 1 & clk $end
$var wire 16 { raddr [15:0] $end
$var wire 1 | re $end
$var wire 16 } waddr [15:0] $end
$var wire 8 ~ wdata [7:0] $end
$var wire 1 !" we $end
$var parameter 32 "" DEPTH $end
$var reg 8 #" q [7:0] $end
$upscope $end
$upscope $end
$scope begin banks[1] $end
$var wire 8 $" w [7:0] $end
$var parameter 2 %" g $end
$scope module mac $end
$var wire 32 &" bias [31:0] $end
$var wire 1 Q clear $end
$var wire 1 & clk $end
$var wire 1 '" enable $end
$var wire 1 ) rst_n $end
$var wire 8 (" w [7:0] $end
$var wire 16 )" product [15:0] $end
$var wire 32 *" extended_product [31:0] $end
$var wire 8 +" a [7:0] $end
$var reg 32 ," acc [31:0] $end
$upscope $end
$scope module weight_bank $end
$var wire 1 & clk $end
$var wire 16 -" raddr [15:0] $end
$var wire 1 ." re $end
$var wire 16 /" waddr [15:0] $end
$var wire 8 0" wdata [7:0] $end
$var wire 1 1" we $end
$var parameter 32 2" DEPTH $end
$var reg 8 3" q [7:0] $end
$upscope $end
$upscope $end
$scope begin banks[2] $end
$var wire 8 4" w [7:0] $end
$var parameter 3 5" g $end
$scope module mac $end
$var wire 32 6" bias [31:0] $end
$var wire 1 Q clear $end
$var wire 1 & clk $end
$var wire 1 7" enable $end
$var wire 1 ) rst_n $end
$var wire 8 8" w [7:0] $end
$var wire 16 9" product [15:0] $end
$var wire 32 :" extended_product [31:0] $end
$var wire 8 ;" a [7:0] $end
$var reg 32 <" acc [31:0] $end
$upscope $end
$scope module weight_bank $end
$var wire 1 & clk $end
$var wire 16 =" raddr [15:0] $end
$var wire 1 >" re $end
$var wire 16 ?" waddr [15:0] $end
$var wire 8 @" wdata [7:0] $end
$var wire 1 A" we $end
$var parameter 32 B" DEPTH $end
$var reg 8 C" q [7:0] $end
$upscope $end
$upscope $end
$scope begin banks[3] $end
$var wire 8 D" w [7:0] $end
$var parameter 3 E" g $end
$scope module mac $end
$var wire 32 F" bias [31:0] $end
$var wire 1 Q clear $end
$var wire 1 & clk $end
$var wire 1 G" enable $end
$var wire 1 ) rst_n $end
$var wire 8 H" w [7:0] $end
$var wire 16 I" product [15:0] $end
$var wire 32 J" extended_product [31:0] $end
$var wire 8 K" a [7:0] $end
$var reg 32 L" acc [31:0] $end
$upscope $end
$scope module weight_bank $end
$var wire 1 & clk $end
$var wire 16 M" raddr [15:0] $end
$var wire 1 N" re $end
$var wire 16 O" waddr [15:0] $end
$var wire 8 P" wdata [7:0] $end
$var wire 1 Q" we $end
$var parameter 32 R" DEPTH $end
$var reg 8 S" q [7:0] $end
$upscope $end
$upscope $end
$scope module input_bank $end
$var wire 1 & clk $end
$var wire 16 T" raddr [15:0] $end
$var wire 1 U" re $end
$var wire 16 V" waddr [15:0] $end
$var wire 8 W" wdata [7:0] $end
$var wire 1 X" we $end
$var parameter 32 Y" DEPTH $end
$var reg 8 Z" q [7:0] $end
$upscope $end
$scope module quant $end
$var wire 32 [" acc [31:0] $end
$var wire 32 \" multiplier [31:0] $end
$var wire 1 l relu $end
$var wire 6 ]" shift [5:0] $end
$var reg 64 ^" half [63:0] $end
$var reg 64 _" magnitude [63:0] $end
$var reg 64 `" product [63:0] $end
$var reg 64 a" rounded [63:0] $end
$var reg 64 b" scaled [63:0] $end
$var reg 8 c" value [7:0] $end
$upscope $end
$upscope $end
$upscope $end
$scope task rd $end
$var reg 8 d" addr [7:0] $end
$var reg 32 e" val [31:0] $end
$upscope $end
$scope task wait_valid $end
$var reg 32 f" s [31:0] $end
$var integer 32 g" timeout [31:0] $end
$upscope $end
$scope task wr $end
$var reg 8 h" addr [7:0] $end
$var reg 32 i" val [31:0] $end
$upscope $end
$upscope $end
$enddefinitions $end
$comment Show the parameter values. $end
$dumpall
b100000000 Y"
b100000000 R"
b11 E"
b100000000 B"
b10 5"
b100000000 2"
b1 %"
b100000000 ""
b0 s
b10 j
b100 i
b0 h
b11 g
b1 f
b100 e
b100000000 d
b100 G
b100 F
b100000000 E
b100000000 D
$end
#0
$dumpvars
bx i"
bx h"
bx g"
bx f"
bx e"
bx d"
bx c"
bx b"
bx a"
bx `"
bx _"
bx ^"
bx ]"
bx \"
bx ["
bx Z"
0X"
b0 W"
bx V"
xU"
bx T"
bx S"
0Q"
b0 P"
bx O"
xN"
bx M"
bx L"
bx K"
bx J"
bx I"
bx H"
xG"
bx F"
bx D"
bx C"
0A"
b0 @"
bx ?"
x>"
bx ="
bx <"
bx ;"
bx :"
bx 9"
bx 8"
x7"
bx 6"
bx 4"
bx 3"
01"
b0 0"
bx /"
x."
bx -"
bx ,"
bx +"
bx *"
bx )"
bx ("
x'"
bx &"
bx $"
bx #"
0!"
b0 ~
bx }
x|
bx {
bx z
bx y
bx x
bx w
bx v
xu
bx t
bx r
bx q
bx p
bx o
bx n
bx m
xl
xk
bx c
xb
bx a
0`
bx _
b0 ^
bx ]
0\
0[
bx Z
b10 Y
b0 X
bx W
bx V
bx U
0T
b0 S
bx R
0Q
xP
xO
xN
b0 M
xL
bx K
bx J
bx I
bx H
1C
xB
xA
x@
x?
bx >
bx =
bx <
x;
b0 :
09
08
07
06
b1111 5
b0 4
bx 3
bx 2
b10110110000100001 1
bx 0
bx /
bx .
bx -
bx ,
b0 +
0*
0)
0(
bx '
0&
b1111 %
b0 $
x#
b0 "
0!
$end
#5000
b0 <
b0 a
b0 c"
b0 a"
b0 b"
b0 ^"
b0 _"
b0 `"
0#
b0 z
b0 >
b0 V
b0 ["
b0 ,"
b0 <"
b0 L"
b0 F"
b0 6"
b0 &"
b0 ]"
b1 \"
b0 t
0@
0A
0l
0?
0k
b0 =
b0 W
b0 o
b0 m
b0 n
b0 {
b0 -"
b0 ="
b0 M"
b0 T"
1b
0B
0;
0U"
0|
0u
0."
0'"
0>"
07"
0N"
0G"
b0 p
b0 H
0P
0O
0N
0L
b0 J
b0 Z
b0 _
b0 I
b0 R
b0 ]
b0 }
b0 /"
b0 ?"
b0 O"
b0 V"
b1 K
b1 U
b100 q
1&
#10000
0&
#15000
b100 q
1&
#20000
0&
#25000
b100 q
1&
#30000
b10 i"
b0 h"
b1 /
b0 3
1)
0&
#35000
1&
#40000
16
17
19
b10 S
b10 W"
b10 ^
b10 ~
b10 0"
b10 @"
b10 P"
1*
b10 +
b10 :
b10 X
0&
#45000
1&
#50000
06
07
09
b1 i"
b1000 h"
0*
0&
#55000
1&
#60000
17
19
b1 S
b1 W"
b1 ^
b1 ~
b1 0"
b1 @"
b1 P"
1*
b1 +
b1 :
b1 X
b1000 $
b1000 4
0&
#65000
1&
#70000
07
09
b0 i"
b1100 h"
0*
0&
#75000
1&
#80000
17
19
b0 S
b0 W"
b0 ^
b0 ~
b0 0"
b0 @"
b0 P"
1*
b0 +
b0 :
b0 X
b1100 $
b1100 4
0&
#85000
1&
#90000
07
09
b10000 h"
b1111111110000100100001101101110 1
b0 .
0*
0&
#95000
1&
#100000
17
19
1*
b10000 $
b10000 4
0&
#105000
1&
#110000
07
09
b11111111111111111111111110000000 i"
b11000 h"
0*
0&
#115000
1&
#120000
1X"
1T
17
19
b10000000 S
b10000000 W"
b10000000 ^
b10000000 ~
b10000000 0"
b10000000 @"
b10000000 P"
1*
b11111111111111111111111110000000 +
b11111111111111111111111110000000 :
b11111111111111111111111110000000 X
b11000 $
b11000 4
0&
#125000
1&
#130000
0X"
0T
07
09
b0 i"
b10100 h"
b0 -
b1 .
0*
0&
#135000
1&
#140000
17
19
b0 S
b0 W"
b0 ^
b0 ~
b0 0"
b0 @"
b0 P"
1*
b0 +
b0 :
b0 X
b10100 $
b10100 4
0&
#145000
1&
#150000
07
09
b11111111111111111111111111110110 i"
b100000 h"
0*
0&
#155000
1&
#160000
1[
17
19
b11110110 S
b11110110 W"
b11110110 ^
b11110110 ~
b11110110 0"
b11110110 @"
b11110110 P"
b0 Y
1*
b11111111111111111111111111110110 +
b11111111111111111111111111110110 :
b11111111111111111111111111110110 X
b100000 $
b100000 4
0&
#165000
b11111111111111111111111111110110 t
1&
#170000
0[
07
09
b1 i"
b100100 h"
0*
0&
#175000
1&
#180000
1[
17
19
b1 S
b1 W"
b1 ^
b1 ~
b1 0"
b1 @"
b1 P"
b1 Y
1*
b1 +
b1 :
b1 X
b100100 $
b100100 4
0&
#185000
1&
#190000
0[
07
09
b0 i"
b101000 h"
0*
0&
#195000
1&
#200000
1[
17
19
b10 Y
b0 S
b0 W"
b0 ^
b0 ~
b0 0"
b0 @"
b0 P"
1*
b0 +
b0 :
b0 X
b101000 $
b101000 4
0&
#205000
1&
#210000
0[
07
09
b10000 h"
b1101111011010101001010100010111 1
b0 .
0*
0&
#215000
1&
#220000
17
19
1*
b10000 $
b10000 4
0&
#225000
1&
#230000
07
09
b11111111111111111111111110000000 i"
b11100 h"
0*
0&
#235000
1&
#240000
1!"
1`
17
19
b10000000 S
b10000000 W"
b10000000 ^
b10000000 ~
b10000000 0"
b10000000 @"
b10000000 P"
1*
b11111111111111111111111110000000 +
b11111111111111111111111110000000 :
b11111111111111111111111110000000 X
b11100 $
b11100 4
0&
#245000
1&
#250000
0!"
0`
07
09
b1 i"
b10100 h"
b1 -
b1 .
0*
0&
#255000
1&
#260000
17
19
b1 S
b1 W"
b1 ^
b1 ~
b1 0"
b1 @"
b1 P"
1*
b1 +
b1 :
b1 X
b10100 $
b10100 4
0&
#265000
b1 J
b1 Z
b1 _
1&
#270000
07
09
b11111111111111111111111111111011 i"
b100000 h"
0*
0&
#275000
1&
#280000
1[
17
19
b11111011 S
b11111011 W"
b11111011 ^
b11111011 ~
b11111011 0"
b11111011 @"
b11111011 P"
b0 Y
1*
b11111111111111111111111111111011 +
b11111111111111111111111111111011 :
b11111111111111111111111111111011 X
b100000 $
b100000 4
0&
#285000
b11111111111111111111111111111011 &"
1&
#290000
0[
07
09
b10 i"
b100100 h"
0*
0&
#295000
1&
#300000
1[
17
19
b10 S
b10 W"
b10 ^
b10 ~
b10 0"
b10 @"
b10 P"
b1 Y
1*
b10 +
b10 :
b10 X
b100100 $
b100100 4
0&
#305000
1&
#310000
0[
07
09
b0 i"
b101000 h"
0*
0&
#315000
1&
#320000
1[
17
19
b10 Y
b0 S
b0 W"
b0 ^
b0 ~
b0 0"
b0 @"
b0 P"
1*
b0 +
b0 :
b0 X
b101000 $
b101000 4
0&
#325000
1&
#330000
0[
07
09
b10000 h"
b110111000000101000111001101100 1
b0 .
0*
0&
#335000
1&
#340000
17
19
1*
b10000 $
b10000 4
0&
#345000
1&
#350000
07
09
b1111111 i"
b11100 h"
0*
0&
#355000
1&
#360000
11"
1`
17
19
b1111111 S
b1111111 W"
b1111111 ^
b1111111 ~
b1111111 0"
b1111111 @"
b1111111 P"
1*
b1111111 +
b1111111 :
b1111111 X
b11100 $
b11100 4
0&
#365000
1&
#370000
01"
0`
07
09
b10 i"
b10100 h"
b10 -
b1 .
0*
0&
#375000
1&
#380000
17
19
b10 S
b10 W"
b10 ^
b10 ~
b10 0"
b10 @"
b10 P"
1*
b10 +
b10 :
b10 X
b10100 $
b10100 4
0&
#385000
b10 J
b10 Z
b10 _
1&
#390000
07
09
b0 i"
b100000 h"
0*
0&
#395000
1&
#400000
1[
17
19
b0 S
b0 W"
b0 ^
b0 ~
b0 0"
b0 @"
b0 P"
b0 Y
1*
b0 +
b0 :
b0 X
b100000 $
b100000 4
0&
#405000
1&
#410000
0[
07
09
b11 i"
b100100 h"
0*
0&
#415000
1&
#420000
1[
17
19
b11 S
b11 W"
b11 ^
b11 ~
b11 0"
b11 @"
b11 P"
b1 Y
1*
b11 +
b11 :
b11 X
b100100 $
b100100 4
0&
#425000
1&
#430000
0[
07
09
b0 i"
b101000 h"
0*
0&
#435000
1&
#440000
1[
17
19
b10 Y
b0 S
b0 W"
b0 ^
b0 ~
b0 0"
b0 @"
b0 P"
1*
b0 +
b0 :
b0 X
b101000 $
b101000 4
0&
#445000
1&
#450000
0[
07
09
b10000 h"
b10111100101100111000100001111101 1
b0 .
0*
0&
#455000
1&
#460000
17
19
1*
b10000 $
b10000 4
0&
#465000
1&
#470000
07
09
b1111111 i"
b11100 h"
0*
0&
#475000
1&
#480000
1A"
1`
17
19
b1111111 S
b1111111 W"
b1111111 ^
b1111111 ~
b1111111 0"
b1111111 @"
b1111111 P"
1*
b1111111 +
b1111111 :
b1111111 X
b11100 $
b11100 4
0&
#485000
1&
#490000
0A"
0`
07
09
b11 i"
b10100 h"
b11 -
b1 .
0*
0&
#495000
1&
#500000
17
19
b11 S
b11 W"
b11 ^
b11 ~
b11 0"
b11 @"
b11 P"
1*
b11 +
b11 :
b11 X
b10100 $
b10100 4
0&
#505000
b11 J
b11 Z
b11 _
1&
#510000
07
09
b101 i"
b100000 h"
0*
0&
#515000
1&
#520000
1[
17
19
b101 S
b101 W"
b101 ^
b101 ~
b101 0"
b101 @"
b101 P"
b0 Y
1*
b101 +
b101 :
b101 X
b100000 $
b100000 4
0&
#525000
b101 F"
1&
#530000
0[
07
09
b100 i"
b100100 h"
0*
0&
#535000
1&
#540000
1[
17
19
b100 S
b100 W"
b100 ^
b100 ~
b100 0"
b100 @"
b100 P"
b1 Y
1*
b100 +
b100 :
b100 X
b100100 $
b100100 4
0&
#545000
1&
#550000
0[
07
09
b0 i"
b101000 h"
0*
0&
#555000
1&
#560000
1[
17
19
b10 Y
b0 S
b0 W"
b0 ^
b0 ~
b0 0"
b0 @"
b0 P"
1*
b0 +
b0 :
b0 X
b101000 $
b101000 4
0&
#565000
1&
#570000
0[
07
09
b10000 h"
b11000010001011111010010100011010 1
b0 .
0*
0&
#575000
1&
#580000
17
19
1*
b10000 $
b10000 4
0&
#585000
1&
#590000
07
09
b1111111 i"
b11100 h"
0*
0&
#595000
1&
#600000
1Q"
1`
17
19
b1111111 S
b1111111 W"
b1111111 ^
b1111111 ~
b1111111 0"
b1111111 @"
b1111111 P"
1*
b1111111 +
b1111111 :
b1111111 X
b11100 $
b11100 4
0&
#605000
1&
